setup.py
Salty.egg-info/PKG-INFO
Salty.egg-info/SOURCES.txt
Salty.egg-info/dependency_links.txt
Salty.egg-info/entry_points.txt
Salty.egg-info/requires.txt
Salty.egg-info/top_level.txt
salty/__init__.py
salty/__main__.py
salty/api.py
salty/config.py
salty/exceptions.py
salty/test_config.py
salty/test_salty.py
salty/version.py