Metadata-Version: 1.0
Name: Salty
Version: 0.1.2
Summary: Password management tool
Home-page: https://github.com/markcial/salty
Author: Mark garcia Sastre
Author-email: markcial@gmail.com
License: UNKNOWN
Platform: UNKNOWN
